{"name":"Sunny",
	"downloads":[
		{
		"title":"SchoolBoy Runaway(Build 16767193)(So Extrair)",
		"uris":["https://pixeldrain.com/api/file/zBAnrN9z?download"],
		"uploadDate":"2025-01-08T10:00:00.000Z",
		"fileSize":"313 MB"},
        {
		"title":"Endoparasitic 2(Build 15897439)(So Extrair)",
		"uris":["https://pixeldrain.com/api/file/Gk5NPkz4?download"],
		"uploadDate":"2025-01-08T10:00:00.000Z",
		"fileSize":"94,7 MB"},
        {
		"title":"Bodycam (Build 16396650 + Online)",
		"uris":["https://gofile.io/d/ko1ShB"],
		"uploadDate":"2025-01-08T10:00:00.000Z",
		"fileSize":"43 GB"}	
        ]
    }	